memory_journal_mcp/__init__.py
memory_journal_mcp/constants.py
memory_journal_mcp/exceptions.py
memory_journal_mcp/models.py
memory_journal_mcp/schema.sql
memory_journal_mcp/server.py
memory_journal_mcp/tool_filtering.py
memory_journal_mcp/utils.py
memory_journal_mcp/vector_search.py
memory_journal_mcp/database/__init__.py
memory_journal_mcp/database/base.py
memory_journal_mcp/database/context.py
memory_journal_mcp/database/operations.py
memory_journal_mcp/database/team_db.py
memory_journal_mcp/github/__init__.py
memory_journal_mcp/github/api.py
memory_journal_mcp/github/cache.py
memory_journal_mcp/github/graphql.py
memory_journal_mcp/github/integration.py
memory_journal_mcp/handlers/__init__.py
memory_journal_mcp/handlers/resources.py
memory_journal_mcp/handlers/prompts/__init__.py
memory_journal_mcp/handlers/prompts/actions_workflows.py
memory_journal_mcp/handlers/prompts/analysis.py
memory_journal_mcp/handlers/prompts/discovery.py
memory_journal_mcp/handlers/prompts/pr_workflows.py
memory_journal_mcp/handlers/prompts/registry.py
memory_journal_mcp/handlers/prompts/reporting.py
memory_journal_mcp/handlers/tools/__init__.py
memory_journal_mcp/handlers/tools/analytics.py
memory_journal_mcp/handlers/tools/entries.py
memory_journal_mcp/handlers/tools/export.py
memory_journal_mcp/handlers/tools/registry.py
memory_journal_mcp/handlers/tools/relationships.py
memory_journal_mcp/handlers/tools/search.py
memory_journal_mcp-2.2.0.dist-info/METADATA
memory_journal_mcp-2.2.0.dist-info/WHEEL
memory_journal_mcp-2.2.0.dist-info/entry_points.txt
memory_journal_mcp-2.2.0.dist-info/licenses/LICENSE
memory_journal_mcp-2.2.0.dist-info/RECORD
