Metadata-Version: 2.4
Name: memory-journal-mcp
Version: 2.2.0
Summary: Project context management for AI-assisted development - Persistent knowledge graphs and intelligent context recall across fragmented AI threads
Project-URL: Homepage, https://github.com/neverinfamous/memory-journal-mcp
Project-URL: Repository, https://github.com/neverinfamous/memory-journal-mcp
Project-URL: Issues, https://github.com/neverinfamous/memory-journal-mcp/issues
Project-URL: Documentation, https://github.com/neverinfamous/memory-journal-mcp/wiki
Author-email: Chris LeRoux <support@adamic.tech>
License: MIT
License-File: LICENSE
Keywords: ai-assistant,context-management,developer-tools,git,github-projects,knowledge-graph,mcp,model-context-protocol,persistent-memory,project-management,thread-continuity
Classifier: Development Status :: 5 - Production/Stable
Classifier: Intended Audience :: Developers
Classifier: License :: OSI Approved :: MIT License
Classifier: Operating System :: OS Independent
Classifier: Programming Language :: Python :: 3
Classifier: Programming Language :: Python :: 3.10
Classifier: Programming Language :: Python :: 3.11
Classifier: Programming Language :: Python :: 3.12
Classifier: Programming Language :: Python :: 3.13
Classifier: Programming Language :: Python :: 3.14
Classifier: Topic :: Security
Classifier: Topic :: Software Development :: Libraries :: Python Modules
Classifier: Topic :: Text Processing
Requires-Python: >=3.10.12
Requires-Dist: mcp>=1.23.0
Requires-Dist: starlette>=0.49.1
Provides-Extra: dev
Requires-Dist: black>=23.0; extra == 'dev'
Requires-Dist: mypy>=1.0; extra == 'dev'
Requires-Dist: pytest>=7.0; extra == 'dev'
